cdocs/__init__.py
cdocs/cdocs.py
cdocs/changer.py
cdocs/concatter.py
cdocs/config.py
cdocs/context.py
cdocs/context_metadata.py
cdocs/contextual_docs.py
cdocs/filer.py
cdocs/finder.py
cdocs/lister.py
cdocs/multi_context_docs.py
cdocs/pather.py
cdocs/physical.py
cdocs/reader.py
cdocs/repl.py
cdocs/simple_concatter.py
cdocs/simple_config.py
cdocs/simple_filer.py
cdocs/simple_finder.py
cdocs/simple_lister.py
cdocs/simple_pather.py
cdocs/simple_reader.py
cdocs/simple_transformer.py
cdocs/transformer.py
cdocs-0.0.42.dist-info/LICENSE
cdocs-0.0.42.dist-info/METADATA
cdocs-0.0.42.dist-info/WHEEL
cdocs-0.0.42.dist-info/RECORD
