Metadata-Version: 2.1
Name: cdocs
Version: 0.0.42
Summary: 
Author: David Kershaw
Author-email: dk107dk@hotmail.com
Requires-Python: >=3.12,<4.0
Classifier: Programming Language :: Python :: 3
Classifier: Programming Language :: Python :: 3.12
Requires-Dist: Jinja2 (==2.11.2)
Requires-Dist: inflect (==4.1.0)
Requires-Dist: markupsafe (==2.0.1)
Requires-Dist: nose (==1.3.3)
Requires-Dist: pypinfo (>=21.0.0,<22.0.0)
